LICENSE
README.md
setup.py
pagseguroCTS/__init__.py
pagseguroCTS/config.py
pagseguroCTS/exceptions.py
pagseguroCTS/parsers.py
pagseguroCTS/utils.py
pagseguroCTS.egg-info/PKG-INFO
pagseguroCTS.egg-info/SOURCES.txt
pagseguroCTS.egg-info/dependency_links.txt
pagseguroCTS.egg-info/top_level.txt