Metadata-Version: 2.1
Name: pagseguroCTS
Version: 0.0.6
Summary: SDK pagseguro
Home-page: https://pypi.org/project/pagseguro/
Author: SDK_PS
Author-email: leopoldo.bernardes@monetizze.com.br
License: MIT License
Keywords: pagseguro
Platform: UNKNOWN
